async_cb_rate/__init__.py
async_cb_rate/errors.py
async_cb_rate/models.py
async_cb_rate/parser.py
async_cb_rate-1.0.1.dist-info/METADATA
async_cb_rate-1.0.1.dist-info/WHEEL
async_cb_rate-1.0.1.dist-info/top_level.txt
async_cb_rate-1.0.1.dist-info/RECORD
