Metadata-Version: 2.1
Name: async-cb-rate
Version: 1.0.1
Summary: Package for async parsing CB rates
Home-page: https://github.com/alenapoliakova/async-cb-rate
Author: Alena Polyakova
Author-email: alenapoliakova2003@gmail.com
Requires-Python: >=3.6
Requires-Dist: bs4 (~=0.0.1)
Requires-Dist: lxml (~=4.9.0)
Requires-Dist: aiohttp (>=3.8.0)
